# 反编译工具

反编译是将字节码转换回 Java 源代码的过程。虽然反编译得到的代码可能与原始代码有所差异，但仍然是理解字节码、分析问题的重要工具。本篇文章介绍常用的反编译工具及其使用方法。

## 为什么要反编译

|为什么要反编译|

**理解框架实现**：学习优秀的开源框架如何实现某个功能。

**排查第三方库问题**：当使用的第三方库出现问题时，反编译可以帮助分析原因。

**代码逆向分析**：在安全审计、兼容性分析等场景中使用。

**学习字节码**：通过反编译结果对照字节码，加深理解。

## javap：JDK 自带工具

|javap|

javap 是 JDK 自带的反编译工具，最基础也最常用。

```bash
# 基本反编译
javap MyClass.class

# 查看详细字节码
javap -v MyClass.class

# 查看行号和局部变量表
javap -l MyClass.class

# 反编译 public 成员
javap -p MyClass.class
```

```bash
# 完整输出示例
Compiled from "BytecodeDemo.java"
public class BytecodeDemo {
  public BytecodeDemo();
    Code:
      0: aload_0
      1: invokespecial #1
      4: return

  public int add(int, int);
    Code:
      0: iload_1
      1: iload_2
      2: iadd
      3: ireturn
}
```

`-v` 参数输出详细的字节码信息，包括常量池、操作数栈、局部变量表等。这是分析字节码最常用的命令。

## jclasslib：IDEA 插件

|jclasslib|

jclasslib 是一个 IDEA 插件，可以图形化地查看字节码信息。安装方法：在 IDEA 的 Plugin 界面搜索 "jclasslib" 并安装。

使用步骤：

1. 在 IDEA 中打开一个 `.class` 文件
2. 点击菜单栏的 "View" -> "Show Bytecode With jclasslib"
3. 在弹出的窗口中查看字节码详情

jclasslib 的优点是图形化展示，直观易懂。可以看到常量池、字段、方法、属性等详细信息。

```
jclasslib 界面结构:

┌─────────────────────────────────────────────────────────────┐
│ Bytecode Browser                                            │
├─────────────────────────────────────────────────────────────┤
│ ├─ Constant Pool                                            │
│ ├─ Interfaces                                               │
│ ├─ Fields                                                   │
│ ├─ Methods                                                  │
│ │   ├─ <init>                                              │
│ │   │   └─ Code                                            │
│ │   │       └─ Exception Table                             │
│ │   └─ add                                                 │
│ │       └─ Code                                            │
│ │           ├─ Stack: 2                                     │
│ │           ├─ Locals: 3                                    │
│ │           └─ Bytecode                                    │
│ └─ Attributes                                               │
└─────────────────────────────────────────────────────────────┘
```

## IDEA 插件：Bytecode Viewer

另一个 IDEA 插件是 "Bytecode Viewer"，可以直接在 IDEA 中查看反编译后的 Java 代码。

安装方法：在 IDEA 的 Plugin 界面搜索 "Bytecode Viewer" 并安装。

使用步骤：

1. 安装插件后，右键点击 `.class` 文件
2. 选择 "Open in Bytecode Viewer"
3. 可以同时查看 Java 源代码、字节码和常量池

## 命令行反编译：cfr / procyon

如果需要将 `.class` 文件反编译为可读的 Java 源代码，可以使用第三方反编译工具。

**cfr** 是一个流行的反编译工具：

```bash
# 下载 cfr
# 使用 cfr 反编译
java -jar cfr.jar MyClass.class --outputdir ./decompiled/

# 反编译整个目录
java -jar cfr.jar ./classes/ --outputdir ./decompiled/
```

**procyon** 是另一个反编译工具：

```bash
# 使用 procyon 反编译
java -jar procyon-decompiler-0.5.30.jar MyClass.class -o ./decompiled/
```

## 常见字节码指令

理解一些常见的字节码指令有助于分析反编译结果：

|指令 |说明 |示例 |
|---|---|---|
| `aload_0` | 加载局部变量 0（this） | |
| `iload_1` | 加载 int 局部变量 1 | |
| `iload_2` | 加载 int 局部变量 2 | |
| `istore_1` | 存储 int 到局部变量 1 | |
| `iadd` | int 加法 | |
| `isub` | int 减法 | |
| `imul` | int 乘法 | |
| `idiv` | int 除法 | |
| `if_icmpgt` | int 比较，大于跳转 | |
| `ireturn` | 返回 int | |
| `invokevirtual` | 调用实例方法 | |
| `invokespecial` | 调用构造器/私有方法 | |
| `invokestatic` | 调用静态方法 | |
| `new` | 创建对象 | |
| `dup` | 复制栈顶值 | |

```java
// 源代码
public int add(int a, int b) {
    return a + b;
}

// 字节码
public int add(int, int);
  Code:
    0: iload_1        // 加载参数 a
    1: iload_2        // 加载参数 b
    2: iadd           // 相加
    3: ireturn        // 返回结果
```

## 实战：分析 JDK 源码

反编译工具的一个实际应用是分析 JDK 源码。虽然 OpenJDK 源码是开放的，但通过反编译可以更直观地理解实现细节。

```bash
# 反编译 String 类
javap -v java.lang.String | head -100

# 查看 String 的 hashCode 方法实现
javap -c -p java.lang.String | grep -A 20 "hashCode"
```

通过反编译分析，可以更深入地理解 JDK 各种类的内部实现，这对于学习优秀的代码设计很有帮助。

**面试追问方向：**

- javap 的 `-c` 和 `-v` 参数有什么区别？
- 如何分析一段字节码的逻辑？
- 反编译在排查问题中有哪些应用？
