import { Badge } from '@rspress/core/theme';

# 程序计数器：线程私有与分支跳转

在 JVM 的内存区域中，程序计数器（Program Counter Register）是最不起眼的一个——它没有堆那么大，没有栈那么复杂，名字听起来也不如"堆"和"栈"直观。但正是这个小小的区域，在 Java 多线程编程中扮演着不可或缺的角色。理解程序计数器，是理解线程调度、CPU 上下文切换、以及为什么 Java 能实现看似"无感"的多线程的基础。

## 为什么需要程序计数器

想象一个没有程序计数器的场景：假设 CPU 正在执行一个方法 A，方法 A 调用了方法 B，方法 B 又调用了方法 C。CPU 在 C 中执行了几条指令后，需要切换到另一个线程去执行其他任务。当 CPU 再次切换回来时，它怎么知道应该从 C 的哪条指令继续执行？应该返回到 B 的哪个位置？B 执行完成后应该返回到 A 的哪个位置？

如果没有额外的记录，CPU 将无法恢复执行现场，一切都将乱套。程序计数器就是解决这个问题的：它就像一个书签，记录了每条线程当前执行到哪条指令。

在实际的物理 CPU 中，程序计数器是一个真实的硬件寄存器。当执行 Java 字节码时，JVM 需要模拟这个寄存器的功能，程序计数器就是 JVM 为每个线程模拟的这个"寄存器"。

## 程序计数器的工作原理

<Badge>PC Register</Badge>

程序计数器是一个很小的内存空间，它可以看作是当前线程所执行的字节码的行号指示器。在虚拟机的概念模型中，字节码解释器通过改变这个计数器的值来选取下一条需要执行的字节码指令。分支、循环、跳转、异常处理、线程恢复等基础功能，都依赖于程序计数器。

```java
public class PCCounterDemo {
    public int compute() {
        int a = 10;
        int b = 20;
        int c = a + b;  // 字节码指令行号可能如下：
        // 0: bipush 10      // 将 10 入栈
        // 2: istore_1       // 弹出栈顶，存入局部变量表 slot 1 (a)
        // 3: bipush 20      // 将 20 入栈
        // 5: istore_2       // 存入 slot 2 (b)
        // 6: iload_1        // 加载 a
        // 7: iload_2        // 加载 b
        // 8: iadd           // 相加
        // 9: istore_3       // 存入 slot 3 (c)
        // 10: iload_3       // 加载 c
        // 11: ireturn       // 返回
        return c;
    }
}
```

当 CPU 执行到 `iload_2`（加载 b）这条指令时，程序计数器的值可能是 7。当方法执行完成后，`ireturn` 指令会弹出程序计数器中保存的返回地址，恢复到调用点的下一条指令继续执行。

## 线程私有与上下文切换

<Badge>Thread</Badge> <Badge>Context Switch</Badge>

Java 是多线程的语言，一个 JVM 进程中有多个线程并发执行。每个线程都有自己的执行栈和程序计数器。为什么程序计数器必须是线程私有的？

考虑这样一个场景：线程 A 和线程 B 都在运行，它们共享同一个 CPU 核心。线程 A 执行到一半，CPU 需要切换到线程 B。当切换回线程 A 时，线程 A 应该从上次中断的地方继续执行，而不是从线程 B 的执行位置继续。

如果程序计数器是线程共享的，线程 A 中断时的计数值会被线程 B 的计数值覆盖，切换回来时将无法恢复现场。所以，程序计数器必须是线程私有的，每个线程都维护自己的程序计数器副本。

```
时间轴:  T1                    T2                    T3
        │                      │                      │
线程A:  ├─[执行到指令5]────────┤[中断，PC=6]──────────┼─[从PC=6恢复执行]
        │                      │                      │
线程B:  │        ├─[执行]─────┼─[中断，PC=12]────────┼─[从PC=12恢复执行]
        │        │             │                      │
CPU:    ├─[执行线程A]─────────┼─[执行线程B]───────────┼─[执行线程A]
```

## Native 方法与程序计数器

对于 Java 方法（字节码），程序计数器保存的是字节码指令的地址。但对于 native 方法（C/C++ 实现的方法），情况有所不同。

当线程执行 native 方法时，程序计数器的值为 undefined（JVM 规范中使用"Undefined"表示）。这是因为 native 方法的执行不经过 JVM 的字节码解释器，而是直接由本地方法库执行。native 方法的执行完全依赖于本地操作系统，JVM 无法也不应该干预其执行流程。

这并不意味着 native 方法执行期间程序计数器没有意义——CPU 仍然有一个真实的程序计数器寄存器来记录执行位置。JVM 只是不再用我们讨论的"程序计数器内存区域"来模拟它。

```java
public class NativeMethodDemo {
    // 这是一个 native 方法
    public native void nativeMethod();
    
    static {
        System.loadLibrary("nativeimpl");
    }
    
    public static void main(String[] args) {
        NativeMethodDemo demo = new NativeMethodDemo();
        
        // 访问普通方法的类加载器
        ClassLoader loader1 = PCCounterDemo.class.getClassLoader();
        System.out.println("PCCounterDemo classLoader: " + loader1);
        
        // 访问 native 方法所在的类加载器
        ClassLoader loader2 = NativeMethodDemo.class.getClassLoader();
        System.out.println("NativeMethodDemo classLoader: " + loader2);
    }
}
```

## 程序计数器与异常处理

程序计数器在异常处理中也扮演重要角色。当字节码执行过程中发生异常时，异常处理器会查询异常表来确定跳转到哪个处理代码。这个查询过程依赖于程序计数器当前指向的指令。

```java
public class ExceptionDemo {
    public void tryCatch() {
        try {
            int result = 10 / 0;  // 触发 ArithmeticException
            System.out.println("不会执行到这里");
        } catch (ArithmeticException e) {
            System.out.println("捕获到除零异常");
        } finally {
            System.out.println("finally 块执行");
        }
    }
}
```

字节码中，异常处理是通过 exception_table（异常表）实现的。每一条异常表记录包括：start_pc（起始位置）、end_pc（结束位置）、handler_pc（处理代码位置）、catch_type（异常类型）。当字节码在 start_pc 到 end_pc 之间发生 catch_type 类型的异常时，跳转到 handler_pc 处执行。程序计数器在这个过程中指示了当前正在执行哪条指令，JVM 据此查找应该跳转到哪个处理器。

## StackOverflowError 与程序计数器

当我们讨论程序计数器时，常常会联想到 StackOverflowError。它们的关联在于：递归调用会导致方法不断嵌套，栈帧不断入栈，最终耗尽栈空间。

```java
public class RecursiveOverflow {
    private static int count = 0;
    
    public static void recursive() {
        count++;
        recursive();  // 无限递归
    }
    
    public static void main(String[] args) {
        try {
            recursive();
        } catch (StackOverflowError e) {
            System.out.println("递归深度: " + count);
            System.out.println("StackOverflowError 发生了");
        }
    }
}
```

StackOverflowError 发生时，程序计数器仍然有意义——它指向了最后执行的那条字节码指令（通常是 `invokevirtual` 或 `invokestatic`）。通过分析这个位置，我们可以定位到是哪个方法导致了溢出。

## 程序计数器的唯一性

在 JVM 的所有内存区域中，程序计数器是唯一一个没有规定任何 OutOfMemoryError 的区域。原因很简单：程序计数器的大小是固定的，它只存储一个指针值（对于 32 位 JVM 是 4 字节，对于 64 位 JVM 是 8 字节），永远不会动态增长。

无论创建多少个线程，每个线程的程序计数器只占用固定的少量内存。这意味着你可以安全地创建数千个线程而不会导致程序计数器内存不足（当然，其他区域如栈可能会成为问题）。

## 面试高频考点

**问题一：什么是程序计数器？它的作用是什么？** 程序计数器是线程私有的内存区域，存储当前线程正在执行的字节码指令的地址。它是线程恢复执行的关键，确保多线程切换后每个线程能从正确的位置恢复执行。

**问题二：为什么程序计数器是线程私有的？** 为了支持多线程的 CPU 时间片轮转调度。当 CPU 切换线程时，需要保存和恢复每个线程的执行状态。程序计数器记录了线程的执行位置，必须是线程私有的才能保证切换的正确性。

**问题三：执行 native 方法时程序计数器是什么状态？** 执行 native 方法时，程序计数器的值是 undefined。因为 native 方法不经过 JVM 的字节码解释器，直接由本地操作系统执行。

**问题四：程序计数器会抛出 OutOfMemoryError 吗？** 不会。程序计数器是固定大小的内存区域，只存储一个指针值，不存在 OOM 的可能。

**问题五：程序计数器和虚拟机栈有什么区别？** 程序计数器是线程私有的，记录当前执行指令的地址；虚拟机栈也是线程私有的，但存储的是方法调用的栈帧信息。程序计数器不会发生 StackOverflowError，虚拟机栈可能会。

程序计数器是 JVM 中最不起眼但最不可或缺的组件。它用很小的内存空间，解决了多线程调度的核心问题。理解程序计数器的工作原理，有助于理解 Java 线程调度的本质，也为后续学习虚拟机栈和字节码执行引擎打下了基础。那么，既然程序计数器如此重要，为什么 JVM 不把它设计成线程共享的呢？
